myscaledb/__init__.py
myscaledb/async_db/__init__.py
myscaledb/async_db/client.py
myscaledb/common/__init__.py
myscaledb/common/_types.pyx
myscaledb/common/exceptions.py
myscaledb/common/records.py
myscaledb/common/sql.py
myscaledb/common/types.py
myscaledb/db/__init__.py
myscaledb/db/client.py
myscaledb/examples/__init__.py
myscaledb/examples/testFunction.py
myscaledb/http_clients/__init__.py
myscaledb/http_clients/abc.py
myscaledb/http_clients/aiohttp.py
myscaledb/http_clients/httpx.py
myscaledb_client-2.0.6.dist-info/LICENSE
myscaledb_client-2.0.6.dist-info/METADATA
myscaledb_client-2.0.6.dist-info/WHEEL
myscaledb_client-2.0.6.dist-info/top_level.txt
myscaledb_client-2.0.6.dist-info/RECORD
