Metadata-Version: 2.1
Name: myscaledb-client
Version: 2.0.6
Summary: Async and sync http MyScale client for python 3.6+
Home-page: https://github.com/myscale/myscaledb-client
Author: MochiXu
Author-email: mochix@moqi.ai
License: MIT
Keywords: clickhouse async sync python aiohttp
Classifier: Development Status :: 5 - Production/Stable
Classifier: Intended Audience :: Developers
Classifier: License :: OSI Approved :: MIT License
Classifier: Natural Language :: English
Classifier: Programming Language :: Python :: 3.6
Classifier: Programming Language :: Python :: 3.7
Classifier: Programming Language :: Python :: 3.8
Classifier: Programming Language :: Python :: 3.9
License-File: LICENSE
Requires-Dist: sqlparse (>=0.3.0)
Requires-Dist: aiodns (>=3.0.0)
Requires-Dist: aiohttp (>=3.0.1)
Requires-Dist: nest-asyncio (~=1.5.6)
Provides-Extra: aiohttp
Requires-Dist: aiohttp (>=3.0.1) ; extra == 'aiohttp'
Provides-Extra: aiohttp-speedups
Requires-Dist: aiodns ; extra == 'aiohttp-speedups'
Requires-Dist: cchardet ; extra == 'aiohttp-speedups'
Requires-Dist: ciso8601 (>=2.1.1) ; extra == 'aiohttp-speedups'
Requires-Dist: aiohttp (>=3.0.1) ; extra == 'aiohttp-speedups'
Provides-Extra: httpx
Requires-Dist: httpx ; extra == 'httpx'
Provides-Extra: httpx-speedups
Requires-Dist: ciso8601 (>=2.1.1) ; extra == 'httpx-speedups'
Requires-Dist: httpx ; extra == 'httpx-speedups'
